quicknet.py
setup.py
quicknet.egg-info/PKG-INFO
quicknet.egg-info/SOURCES.txt
quicknet.egg-info/dependency_links.txt
quicknet.egg-info/top_level.txt