Metadata-Version: 1.0
Name: quicknet
Version: 3.0
Summary: Collection of methods for a quick start with neural networks.
Home-page: UNKNOWN
Author: Stratis Markou
Author-email: stratismar@gmail.com
License: UNKNOWN
Platform: UNKNOWN
